.coveragerc
.flake8
.gitignore
.travis.yml
AUTHORS.md
CITATION
LICENSE.txt
MANIFEST.in
README.rst
requirements.txt
setup.cfg
setup.py
.github/ISSUE_TEMPLATE/bug_report.md
.github/ISSUE_TEMPLATE/feature_request.md
doc/Makefile
doc/make.bat
doc/source/conf.py
doc/source/index.rst
doc/source/install.rst
doc/source/overview.rst
doc/source/satpy_usage.rst
doc/source/usage.rst
doc/source/_static/theme_overrides.css
doc/source/api/textory.rst
tests/test_statistics.py
tests/test_textures.py
tests/test_util.py
textory/__init__.py
textory/statistics.py
textory/textures.py
textory/util.py
textory/wrappers.py
textory.egg-info/PKG-INFO
textory.egg-info/SOURCES.txt
textory.egg-info/dependency_links.txt
textory.egg-info/requires.txt
textory.egg-info/top_level.txt