Metadata-Version: 1.2
Name: textory
Version: 0.2.7b0
Summary: Image Textures
Home-page: https://github.com/benr0/textory
Author: Benjamin Roesner
Author-email: benjamin.roesner@geo.uni-marburg.de
License: UNKNOWN
Platform: UNKNOWN
Classifier: Programming Language :: Python
Classifier: Development Status :: 4 - Beta
Classifier: Intended Audience :: Science/Research
Classifier: License :: OSI Approved :: GNU General Public License v3 or later (GPLv3+)
Classifier: Operating System :: OS Independent
Classifier: Topic :: Scientific/Engineering
Requires-Python: >=3.7
